reforis_distutils/__init__.py
reforis_distutils-0.1.1.dist-info/METADATA
reforis_distutils-0.1.1.dist-info/WHEEL
reforis_distutils-0.1.1.dist-info/top_level.txt
reforis_distutils-0.1.1.dist-info/RECORD
